requests_ms_auth/__init__.py
requests_ms_auth/session.py
requests_ms_auth-0.0.7.dist-info/LICENSE
requests_ms_auth-0.0.7.dist-info/METADATA
requests_ms_auth-0.0.7.dist-info/WHEEL
requests_ms_auth-0.0.7.dist-info/top_level.txt
requests_ms_auth-0.0.7.dist-info/RECORD
