Metadata-Version: 2.1
Name: requests-ms-auth
Version: 0.0.7
Summary: Python requests session for microsoft with support for oauth2, adal and msal
Home-page: https://github.com/equinor/requests_ms_auth
Author: Lennart Rolland
Author-email: lennartrolland@gmail.com
License: AGPL-3.0
Download-URL: https://github.com/equinor/requests_ms_auth/dist/requests_ms_auth-0.0.7.tar.gz
Platform: UNKNOWN
Classifier: Intended Audience :: Developers
Classifier: Topic :: Utilities
Classifier: License :: OSI Approved :: GNU Affero General Public License v3
Classifier: Natural Language :: English
Classifier: Operating System :: POSIX :: Linux
Classifier: Programming Language :: Python :: 3
Classifier: Programming Language :: Python :: 3.4
Classifier: Programming Language :: Python :: 3.5
Classifier: Programming Language :: Python :: 3.6
Classifier: Programming Language :: Python :: 3.7
Classifier: Programming Language :: Python :: 3.8
Requires-Python: >=3.4.0
Requires-Dist: adal (~=1.2)
Requires-Dist: msal (~=1.1.0)
Requires-Dist: requests (>=2.0.0)
Requires-Dist: requests-oauthlib (~=1.2.0)
